LICENSE.txt
README.md
setup.py
rulu/__init__.py
rulu/actions.py
rulu/aggregations.py
rulu/auto_salience.py
rulu/builtin_aggregations.py
rulu/class_.py
rulu/clips_func.py
rulu/conditional_expr.py
rulu/def_module_loader.py
rulu/engine.py
rulu/expr.py
rulu/fact.py
rulu/func.py
rulu/operators.py
rulu/progress_bar.py
rulu/rule.py
rulu/ruledef.py
rulu/rulu_io.py
rulu/slots.py
rulu/typedefs.py
rulu/utils.py
rulu/xls_export.py
rulu.egg-info/PKG-INFO
rulu.egg-info/SOURCES.txt
rulu.egg-info/dependency_links.txt
rulu.egg-info/requires.txt
rulu.egg-info/top_level.txt
test/test_io.py
test/test_ruleengine.py