Metadata-Version: 2.1
Name: rulu
Version: 0.31
Summary: Python interface for building rule-based expert systems over clipspy
Home-page: http://github.com/ubarkai/rulu
Author: Uri Barkai
Author-email: ubarkai@gmail.com
License: LGPL
Provides-Extra: testing
License-File: LICENSE.txt
